common_utils/__init__.py
common_utils/common_utils_impl.py
common_utils_xcc-0.0.2.dist-info/METADATA
common_utils_xcc-0.0.2.dist-info/WHEEL
common_utils_xcc-0.0.2.dist-info/top_level.txt
common_utils_xcc-0.0.2.dist-info/RECORD
