Metadata-Version: 2.1
Name: common_utils_xcc
Version: 0.0.2
Summary: Common Utility Python package
Home-page: UNKNOWN
Author: Xiaoyu Charles Chen
Author-email: x.chen@sky.com
License: UNKNOWN
Keywords: python3,common_utils
Platform: UNKNOWN
Classifier: Development Status :: 3 - Alpha
Classifier: Intended Audience :: Developers
Classifier: Programming Language :: Python :: 3
Classifier: Operating System :: MacOS :: MacOS X
Classifier: Operating System :: Microsoft :: Windows
